{
  "disclaimer": "Usage subject to terms: https://openexchangerates.org/terms",
  "license": "https://openexchangerates.org/license",
  "timestamp": 1293901200,
  "base": "USD",
  "rates": {
    "AED": 3.672725,
    "AFN": 43.022128,
    "ALL": 104.57501,
    "AMD": 363.231524,
    "ANG": 1.79075,
    "AOA": 92.405819,
    "ARS": 3.970868,
    "AUD": 0.980253,
    "AWG": 1.79025,
    "AZN": 0.797344,
    "BAM": 1.463638,
    "BBD": 2,
    "BDT": 70.60861,
    "BGN": 1.463725,
    "BHD": 0.376515,
    "BIF": 1127.327668,
    "BMD": 1,
    "BND": 1.285783,
    "BOB": 6.955924,
    "BRL": 1.660604,
    "BSD": 1,
    "BTN": 44.686316,
    "BWP": 6.468699,
    "BYR": 2997.122149,
    "BZD": 1.9875,
    "CAD": 0.997228,
    "CDF": 887.270181,
    "CHF": 0.933819,
    "CLP": 467.810748,
    "CNY": 6.598653,
    "COP": 1953.710641,
    "CRC": 506.586056,
    "CVE": 82.519084,
    "CZK": 18.742763,
    "DJF": 177.721,
    "DKK": 5.573621,
    "DOP": 37.214215,
    "DZD": 74.519292,
    "EEK": 11.666462,
    "EGP": 5.803494,
    "ETB": 12.710642,
    "EUR": 0.747736,
    "FJD": 1.842895,
    "FKP": 0.642344,
    "GBP": 0.642344,
    "GEL": 1.772175,
    "GHS": 1.484464,
    "GIP": 0.644178,
    "GMD": 27.243245,
    "GNF": 6996.949675,
    "GTQ": 8.012668,
    "GYD": 203.124509,
    "HKD": 7.77303,
    "HNL": 18.92,
    "HRK": 5.546085,
    "HTG": 39.992614,
    "HUF": 207.742079,
    "IDR": 8995.65093,
    "IEP": 0.693643,
    "ILS": 3.544278,
    "INR": 44.663684,
    "IQD": 1169.782492,
    "IRR": 10352.07918,
    "ISK": 115.00751,
    "JMD": 86.599452,
    "JOD": 0.708375,
    "JPY": 81.112689,
    "KES": 80.6511,
    "KGS": 47.081524,
    "KHR": 4032.635092,
    "KMF": 368.184404,
    "KPW": 143.065322,
    "KRW": 1120.851876,
    "KWD": 0.281408,
    "KZT": 147.295106,
    "LAK": 8032.014818,
    "LBP": 1501.970716,
    "LKR": 110.940641,
    "LRD": 69.973993,
    "LSL": 6.604899,
    "LTL": 2.584044,
    "LVL": 0.525972,
    "LYD": 1.250035,
    "MAD": 8.352851,
    "MDL": 12.069231,
    "MGA": 2119.861293,
    "MKD": 45.924562,
    "MMK": 6.51,
    "MNT": 1230.3812,
    "MOP": 8.009082,
    "MRO": 281.311256,
    "MUR": 30.123553,
    "MVR": 12.8,
    "MWK": 150.86769,
    "MXN": 12.365375,
    "MYR": 3.067831,
    "MZN": 32.348202,
    "NAD": 6.640593,
    "NGN": 152.172544,
    "NIO": 19.819738,
    "NOK": 5.830575,
    "NPR": 70.471542,
    "NZD": 1.284561,
    "OMR": 0.384497,
    "PAB": 1,
    "PEN": 2.805864,
    "PGK": 2.593892,
    "PHP": 43.660152,
    "PKR": 85.66927,
    "PLN": 2.974854,
    "PYG": 4622.276553,
    "QAR": 3.64,
    "RON": 3.210221,
    "RSD": 79.037164,
    "RUB": 30.668791,
    "RWF": 588.221583,
    "SAR": 3.749725,
    "SBD": 7.970465,
    "SCR": 12.162533,
    "SDG": 2.497837,
    "SEK": 6.710305,
    "SGD": 1.282922,
    "SHP": 0.642344,
    "SLL": 4146.503738,
    "SOS": 1600.001489,
    "SRD": 2.709819,
    "STD": 18370.721936,
    "SVC": 8.746457,
    "SYP": 46.800087,
    "SZL": 6.600953,
    "THB": 30.066313,
    "TJS": 4.402614,
    "TMT": 2.826548,
    "TND": 1.416282,
    "TOP": 1.868371,
    "TRY": 1.54161,
    "TTD": 6.32025,
    "TWD": 29.134436,
    "TZS": 1500.205508,
    "UAH": 7.964996,
    "UGX": 2326.081118,
    "USD": 1,
    "UYU": 19.849337,
    "UZS": 1653.277952,
    "VEF": 4.3,
    "VND": 19448.708202,
    "VUV": 91.988865,
    "WST": 2.33672,
    "XAF": 498.50615,
    "XCD": 2.691726,
    "XDR": 0.649095,
    "XOF": 493.00615,
    "XPF": 90.053383,
    "YER": 213.87153,
    "ZAR": 6.622288,
    "ZMK": 4797.421008,
    "ZWD": 15180.687951
  }
}